mcp_pdf_forms/__init__.py
mcp_pdf_forms/server.py
mcp_pdf_forms-0.2.0.dist-info/METADATA
mcp_pdf_forms-0.2.0.dist-info/WHEEL
mcp_pdf_forms-0.2.0.dist-info/entry_points.txt
mcp_pdf_forms-0.2.0.dist-info/RECORD
