Metadata-Version: 2.4
Name: mcp_pdf_forms
Version: 0.2.0
Summary: PDF form manipulation toolkit built with MCP and PyMuPDF
Project-URL: Repository, https://github.com/Wildebeest/mcp_pdf_forms
Project-URL: Documentation, https://github.com/Wildebeest/mcp_pdf_forms#readme
Author-email: Wilde <wilde@example.com>
License: MIT
Requires-Python: >=3.11
Requires-Dist: mcp[cli]>=1.3.0
Requires-Dist: pillow>=11.1.0
Requires-Dist: pymupdf>=1.25.3
Provides-Extra: test
Requires-Dist: pytest>=7.0.0; extra == 'test'
